uninhibited/__init__.py
uninhibited/async.py
uninhibited/containers.py
uninhibited/dispatch.py
uninhibited/events.py
uninhibited/events_async.py
uninhibited/utils.py
uninhibited/async/__init__.py
uninhibited-1.0.4.dist-info/DESCRIPTION.rst
uninhibited-1.0.4.dist-info/METADATA
uninhibited-1.0.4.dist-info/RECORD
uninhibited-1.0.4.dist-info/WHEEL
uninhibited-1.0.4.dist-info/metadata.json
uninhibited-1.0.4.dist-info/pbr.json
uninhibited-1.0.4.dist-info/top_level.txt
