Metadata-Version: 2.0
Name: uninhibited
Version: 1.0.4
Summary: Dead simple event handling for Python 2/3; minus the straight jacket.
Home-page: https://github.com/akatrevorjay/uninhibited
Author: Trevor Joynson
Author-email: github@skywww.net
License: GPL
Keywords: event
Requires-Dist: six
Requires-Dist: sortedcontainers
